{
  "Donald Trump": "donald-trump.jpg",
  "Ghislaine Maxwell": "ghislaine-maxwell.jpg",
  "Jes Staley": "jes-staley.jpg",
  "Karyna Shuliak": "karyna-shuliak.jpg",
  "Oren, Alon, and Tal Alexander": "oren-alon-and-tal-alexander.png",
  "Pregnant": "pregnant.jpg",
  "Ramsey Elkholy": "ramsey-elkholy.png",
  "Sultan Bin Sulayem": "sultan-bin-sulayem.jpg",
  "Leon Black": "leon-black.png",
  "Prince Andrew": "prince-andrew.png",
  "Eva Andersson-Dubin": "eva-andersson-dubin.png",
  "Leslie Groff": "leslie-groff.png",
  "Whoops": "whoops.png",
  "Peggy Siegal": "peggy-siegal.png",
  "Bill Richardson": "bill-richardson.jpg",
  "Dangene and Jennie Enterprise": "dangene-and-jennie-enterprise.png",
  "Gynecologist": "gynecologist.png",
  "William Riley": "william-riley.png",
  "Bill Clinton": "bill-clinton.jpg",
  "Glenn Dubin": "glenn-dubin.png",
  "Michael Wolff": "michael-wolff.png",
  "Ehud Barak": "ehud-barak.png",
  "Peter Mandelson": "peter-mandelson.jpg",
  "Israel and Mossad": "israel-and-mossad.png",
  "Steve Bannon": "steve-bannon.png",
  "Les Wexner": "les-wexner.png",
  "Epstein Suicide": "epstein-suicide.png",
  "Sarah Ferguson": "sarah-ferguson.jpg",
  "Ron Lauder": "ron-lauder.png",
  "Corina Tarnita": "corina-tarnita.png",
  "Lana Zakocela": "lana-zakocela.jpg",
  "Susan Hamblin": "susan-hamblin.png",
  "Drugs": "drugs.jpg",
  "Larry Summers": "larry-summers.png",
  "Peter Theil": "peter-theil.png",
  "Bill Gates": "bill-gates.png",
  "Elon Musk": "elon-musk.jpg",
  "Howard Lutnick": "howard-lutnick.png",
  "Francis Derby": "francis-derby.png",
  "Casey Wasserman": "casey-wasserman.png",
  "Leon Botstein": "leon-botstein.jpg",
  "Kathryn Ruemmler": "kathryn-ruemmler.png",
  "Peter Attia": "peter-attia.png",
  "Jess Ting": "jess-ting.png",
  "Qatar": "qatar.jpg",
  "Jeff Bezos": "jeff-bezos.png",
  "Paolo Zampolli": "paolo-zampolli.png",
  "Chuck Schumer": "chuck-schumer.png",
  "Rupert Murdoch": "rupert-murdoch.jpg",
  "Stefan Krause": "stefan-krause.png",
  "Sheikh Sultan Bin Jassim Al Thani": "sheikh-sultan-bin-jassim-al-thani.png",
  "Mark Zuckerberg": "mark-zuckerberg.png",
  "Beef Jerky": "beef-jerky.png",
  "Cream Cheese": "cream-cheese.jpg",
  "Baal and Occult References": "baal-and-occult-references.png",
  "Hillary Clinton": "hillary-clinton.png",
  "9/11": "9-11.png",
  "Kevin O'Leary": "kevin-o-leary.jpg",
  "Pam Bondi": "pam-bondi.png",
  "Oprah": "oprah.png",
  "George H.W. Bush and George W. Bush": "george-h-w-bush-and-george-w-bush.png",
  "Stanislas Nordey": "stanislas-nordey.jpg",
  "Bill O'Reilly": "bill-o-reilly.jpg",
  "Kash Patel": "kash-patel.png",
  "Betsy DeVos": "betsy-devos.png",
  "Benjamin Netanyahu": "benjamin-netanyahu.jpg",
  "Bill Maher": "bill-maher.png",
  "Justice Clarence Thomas": "justice-clarence-thomas.png",
  "Ellen DeGeneres": "ellen-degeneres.png",
  "John and Tony Podesta": "john-and-tony-podesta.jpg",
  "Justin Trudeau": "justin-trudeau.png",
  "Larry Silverstein": "larry-silverstein.png",
  "Lifetouch": "lifetouch.png",
  "Mark Landon": "mark-landon.png",
  "Barack Obama": "barack-obama.jpg",
  "RFK": "rfk.png",
  "Savannah Guthrie": "savannah-guthrie.png",
  "Ted Leonsis": "ted-leonsis.png",
  "Tom Hanks": "tom-hanks.jpg"
}